{"name": "THANK_YOU", "fps": 30.0, "duration": 1.4, "two_handed": false, "anchorJoint": "Head", "dom": {"kind": "open", "ext": [1.0, 1.0, 1.0, 1.0], "thumb": 1.0, "measured": {"flex": [0.0, 0.0, 0.0, 0.0]}}, "ndom": null, "palmFace": [0.0, 0.0, -1.0], "palmFaceN": null, "frames": [{"dom": [0.0, -0.2459, 0.2285]}, {"dom": [0.0, -0.2462, 0.2289]}, {"dom": [0.0, -0.247, 0.2299]}, {"dom": [0.0, -0.2485, 0.2316]}, {"dom": [0.0, -0.2505, 0.2339]}, {"dom": [0.0, -0.2531, 0.2369]}, {"dom": [0.0, -0.2562, 0.2405]}, {"dom": [0.0, -0.2598, 0.2448]}, {"dom": [0.0, -0.264, 0.2496]}, {"dom": [0.0, -0.2686, 0.255]}, {"dom": [0.0, -0.2737, 0.2609]}, {"dom": [0.0, -0.2792, 0.2674]}, {"dom": [0.0, -0.2851, 0.2743]}, {"dom": [0.0, -0.2913, 0.2816]}, {"dom": [0.0, -0.2979, 0.2893]}, {"dom": [0.0, -0.3048, 0.2973]}, {"dom": [0.0, -0.312, 0.3056]}, {"dom": [0.0, -0.3193, 0.3142]}, {"dom": [0.0, -0.3268, 0.323]}, {"dom": [0.0, -0.3345, 0.3319]}, {"dom": [0.0, -0.3422, 0.3409]}, {"dom": [0.0, -0.35, 0.35]}, {"dom": [0.0, -0.3578, 0.3591]}, {"dom": [0.0, -0.3655, 0.3681]}, {"dom": [0.0, -0.3732, 0.377]}, {"dom": [0.0, -0.3807, 0.3858]}, {"dom": [0.0, -0.388, 0.3944]}, {"dom": [0.0, -0.3952, 0.4027]}, {"dom": [0.0, -0.4021, 0.4107]}, {"dom": [0.0, -0.4087, 0.4184]}, {"dom": [0.0, -0.4149, 0.4257]}, {"dom": [0.0, -0.4208, 0.4326]}, {"dom": [0.0, -0.4263, 0.4391]}, {"dom": [0.0, -0.4314, 0.445]}, {"dom": [0.0, -0.436, 0.4504]}, {"dom": [0.0, -0.4402, 0.4552]}, {"dom": [0.0, -0.4438, 0.4595]}, {"dom": [0.0, -0.4469, 0.4631]}, {"dom": [0.0, -0.4495, 0.4661]}, {"dom": [0.0, -0.4515, 0.4684]}, {"dom": [0.0, -0.453, 0.4701]}, {"dom": [0.0, -0.4538, 0.4711]}, {"dom": [0.0, -0.4541, 0.4715]}]}